dataform/__init__.py
dataform/audio.py
dataform/core.py
dataform/image.py
dataform/text.py
dataform/version.py
dataform/video.py
dataform-1.0.0.dist-info/LICENSE
dataform-1.0.0.dist-info/METADATA
dataform-1.0.0.dist-info/WHEEL
dataform-1.0.0.dist-info/top_level.txt
dataform-1.0.0.dist-info/RECORD
