Metadata-Version: 2.1
Name: dataform
Version: 1.0.0
Summary: DataForm: Data processing and transformation tool.
Home-page: https://github.com/Yuan-ManX/dataform
Author: Yuan Man
Author-email: ym1076302261@gmail.com
License: MIT
Keywords: machinelearning deeplearning artificialintelligence neuralnetworks dataprocessing data
Platform: UNKNOWN
Classifier: Development Status :: 3 - Alpha
Classifier: Intended Audience :: Developers
Classifier: Intended Audience :: Science/Research
Classifier: License :: OSI Approved :: MIT License
Classifier: Topic :: Scientific/Engineering :: Artificial Intelligence
Classifier: Programming Language :: Python :: 3
Classifier: Programming Language :: Python :: 3.6
Classifier: Programming Language :: Python :: 3.7
Classifier: Programming Language :: Python :: 3.8
Classifier: Programming Language :: Python :: 3.9
Classifier: Programming Language :: Python :: 3.10
Classifier: Programming Language :: Python :: 3.11
License-File: LICENSE
Requires-Dist: numpy
Requires-Dist: pydub
Requires-Dist: PIL
Requires-Dist: PyPDF2
Requires-Dist: opencv-python
Requires-Dist: Pillow
